{
    "id": "shell",
    "version": "1.0.0",
    "name": "Shell Environment",
    "description": "Configurable shell with optional Zsh, Oh My Zsh, Powerlevel10k, autosuggestions, and syntax highlighting.",
    "options": {
        "installZsh": {
            "type": "boolean",
            "default": true,
            "description": "Install Zsh and set as default shell"
        },
        "ohMyZsh": {
            "type": "boolean",
            "default": true,
            "description": "Install Oh My Zsh framework"
        },
        "powerlevel10k": {
            "type": "boolean",
            "default": true,
            "description": "Install Powerlevel10k theme"
        },
        "autosuggestions": {
            "type": "boolean",
            "default": true,
            "description": "Enable zsh-autosuggestions"
        },
        "syntaxHighlighting": {
            "type": "boolean",
            "default": true,
            "description": "Enable zsh-syntax-highlighting"
        },
        "opinionated": {
            "type": "boolean",
            "default": false,
            "description": "Apply opinionated Zsh and Powerlevel10k settings"
        }
    },
    "entrypoint": "install.sh"
}